ckanext_files-1.0.0-py3.12-nspkg.pth
ckanext/file_upload_widget/__init__.py
ckanext/file_upload_widget/helpers.py
ckanext/file_upload_widget/plugin.py
ckanext/files/__init__.py
ckanext/files/base.py
ckanext/files/config.py
ckanext/files/config_declaration.yaml
ckanext/files/helpers.py
ckanext/files/interfaces.py
ckanext/files/plugin.py
ckanext/files/shared.py
ckanext/files/signals.py
ckanext/files/task.py
ckanext/files/types.py
ckanext/files/utils.py
ckanext/files/views.py
ckanext/files/assets/resource.config
ckanext/files/assets/webassets.yml
ckanext/files/assets/scripts/files--google-cloud-storage-uploader.js
ckanext/files/assets/scripts/files--modules.js
ckanext/files/assets/scripts/files--s3.js
ckanext/files/assets/scripts/files--shared-uploader.js
ckanext/files/assets/scripts/files--shared.js
ckanext/files/assets/styles/files--style.css
ckanext/files/cli/__init__.py
ckanext/files/cli/dev.py
ckanext/files/cli/file.py
ckanext/files/cli/maintain.py
ckanext/files/cli/migrate.py
ckanext/files/cli/stats.py
ckanext/files/cli/storage.py
ckanext/files/logic/__init__.py
ckanext/files/logic/action.py
ckanext/files/logic/auth.py
ckanext/files/logic/schema.py
ckanext/files/logic/validators.py
ckanext/files/migration/files/alembic.ini
ckanext/files/migration/files/env.py
ckanext/files/migration/files/script.py.mako
ckanext/files/migration/files/versions/001_cc1a832108c5_create_files_table.py
ckanext/files/migration/files/versions/002_2c5f1f90888c_add_file_last_access_field.py
ckanext/files/migration/files/versions/003_5851e09b7ca3_remove_path_rename_kind_add_stats.py
ckanext/files/migration/files/versions/004_3c69eb68cecd_create_upload_table.py
ckanext/files/migration/files/versions/005_2fbd30a1b364_create_owner_table.py
ckanext/files/migration/files/versions/006_64ca007bf3eb_merge_upload_and_file_models.py
ckanext/files/migration/files/versions/007_76fdef67f479_add_access_column_to_owner_table.py
ckanext_files-1.0.0.dist-info/licenses/LICENSE
ckanext_files-1.0.0.dist-info/METADATA
ckanext_files-1.0.0.dist-info/WHEEL
ckanext_files-1.0.0.dist-info/entry_points.txt
ckanext_files-1.0.0.dist-info/namespace_packages.txt
ckanext_files-1.0.0.dist-info/top_level.txt
ckanext_files-1.0.0.dist-info/RECORD
